setriq-1.6.4.dist-info/top_level.txt
setriq-1.6.4.dist-info/WHEEL
setriq-1.6.4.dist-info/RECORD
setriq-1.6.4.dist-info/LICENSE
setriq-1.6.4.dist-info/METADATA
setriq.libs/libgcc_s-4e37474d.so.1
setriq.libs/libstdc++-fd9f4683.so.6.0.28
setriq/__init__.py
setriq/_C.cpython-37m-aarch64-linux-gnu.so
setriq/_C/python_wrapper.cpp
setriq/_C/metrics/OptimalStringAlignment.cpp
setriq/_C/metrics/JaroWinkler.cpp
setriq/_C/metrics/CdrDist.cpp
setriq/_C/metrics/Levenshtein.cpp
setriq/_C/metrics/Jaro.cpp
setriq/_C/metrics/TcrDist.cpp
setriq/_C/metrics/Hamming.cpp
setriq/_C/metrics/LongestCommonSubstring.cpp
setriq/_C/alignment/SubstitutionMatrix.cpp
setriq/_C/alignment/SmithWaterman.cpp
setriq/modules/__init__.py
setriq/modules/distances.py
setriq/modules/substitution.py
setriq/modules/utils.py
setriq/modules/single_dispatch.py
setriq/data/blosum-45.json
setriq/data/blosum-90.json
setriq/data/blosum-62.json
