Metadata-Version: 2.1
Name: setriq
Version: 1.6.4
Summary: Python package written in C++ for pairwise distance computation for sequences.
Home-page: https://github.com/BenTenmann/setriq
Author: benjamin-tenmann
Author-email: b.tenmann@me.com
License: MIT
Platform: UNKNOWN
Classifier: Development Status :: 3 - Alpha
Classifier: Intended Audience :: Developers
Classifier: Topic :: Software Development :: Build Tools
Classifier: License :: OSI Approved :: MIT License
Classifier: Programming Language :: Python :: 3
Classifier: Programming Language :: Python :: 3.7
Classifier: Programming Language :: Python :: 3.8
Classifier: Programming Language :: Python :: 3.9
Requires-Python: >=3.7,<3.10
License-File: LICENSE
